dflow/__init__.py
dflow/client.py
dflow/py.typed
dflow/api/__init__.py
dflow/api/metadata/__init__.py
dflow/api/metadata/events.py
dflow/api/metadata/live_data.py
dflow/api/metadata/markets.py
dflow/api/metadata/orderbook.py
dflow/api/metadata/search.py
dflow/api/metadata/series.py
dflow/api/metadata/sports.py
dflow/api/metadata/tags.py
dflow/api/metadata/trades.py
dflow/api/trade/__init__.py
dflow/api/trade/intent.py
dflow/api/trade/orders.py
dflow/api/trade/prediction_market.py
dflow/api/trade/swap.py
dflow/api/trade/tokens.py
dflow/api/trade/venues.py
dflow/solana/__init__.py
dflow/solana/positions.py
dflow/solana/transactions.py
dflow/types/__init__.py
dflow/types/common.py
dflow/types/events.py
dflow/types/live_data.py
dflow/types/markets.py
dflow/types/orderbook.py
dflow/types/orders.py
dflow/types/search.py
dflow/types/series.py
dflow/types/solana.py
dflow/types/tags.py
dflow/types/tokens.py
dflow/types/trades.py
dflow/types/venues.py
dflow/types/websocket.py
dflow/utils/__init__.py
dflow/utils/constants.py
dflow/utils/http.py
dflow/utils/pagination.py
dflow/utils/retry.py
dflow/websocket/__init__.py
dflow/websocket/client.py
dflow_sdk-0.1.6.dist-info/METADATA
dflow_sdk-0.1.6.dist-info/WHEEL
dflow_sdk-0.1.6.dist-info/licenses/LICENSE
dflow_sdk-0.1.6.dist-info/RECORD
