Metadata-Version: 2.4
Name: dflow-sdk
Version: 0.1.6
Summary: Python SDK for DFlow on Solana - prediction markets and trading
Project-URL: Homepage, https://dflow-sdk.vercel.app
Project-URL: Documentation, https://dflow-sdk.vercel.app/docs
Project-URL: Repository, https://github.com/vaibhav0806/dflow-sdk
Project-URL: Issues, https://github.com/vaibhav0806/dflow-sdk/issues
Author-email: DFlow Team <dev@dflow.net>
Maintainer-email: Vaibhav <vaibhav@dflow.net>
License: MIT
License-File: LICENSE
Keywords: blockchain,crypto,defi,dflow,kalshi,prediction-markets,sdk,solana,trading,web3
Classifier: Development Status :: 4 - Beta
Classifier: Intended Audience :: Developers
Classifier: Intended Audience :: Financial and Insurance Industry
Classifier: License :: OSI Approved :: MIT License
Classifier: Operating System :: OS Independent
Classifier: Programming Language :: Python :: 3
Classifier: Programming Language :: Python :: 3.10
Classifier: Programming Language :: Python :: 3.11
Classifier: Programming Language :: Python :: 3.12
Classifier: Programming Language :: Python :: 3.13
Classifier: Topic :: Internet :: WWW/HTTP :: HTTP Servers
Classifier: Topic :: Office/Business :: Financial :: Investment
Classifier: Topic :: Software Development :: Libraries :: Python Modules
Classifier: Typing :: Typed
Requires-Python: >=3.10
Requires-Dist: httpx>=0.27.0
Requires-Dist: pydantic>=2.0.0
Requires-Dist: solana>=0.34.0
Requires-Dist: solders>=0.21.0
Requires-Dist: twine>=6.2.0
Requires-Dist: websockets>=12.0
Provides-Extra: dev
Requires-Dist: mypy>=1.13.0; extra == 'dev'
Requires-Dist: pytest-asyncio>=0.24.0; extra == 'dev'
Requires-Dist: pytest-httpx>=0.30.0; extra == 'dev'
Requires-Dist: pytest>=8.0.0; extra == 'dev'
Requires-Dist: ruff>=0.8.0; extra == 'dev'
